[{"trends":[{"name":"#TDF2020","url":"http:\/\/twitter.com\/search?q=%23TDF2020","promoted_content":null,"query":"%23TDF2020","tweet_volume":12079},{"name":"#pompiers","url":"http:\/\/twitter.com\/search?q=%23pompiers","promoted_content":null,"query":"%23pompiers","tweet_volume":null},{"name":"#SkyrockDedicace","url":"http:\/\/twitter.com\/search?q=%23SkyrockDedicace","promoted_content":null,"query":"%23SkyrockDedicace","tweet_volume":null},{"name":"De Ligt","url":"http:\/\/twitter.com\/search?q=%22De+Ligt%22","promoted_content":null,"query":"%22De+Ligt%22","tweet_volume":null},{"name":"#tourdefrance2020","url":"http:\/\/twitter.com\/search?q=%23tourdefrance2020","promoted_content":null,"query":"%23tourdefrance2020","tweet_volume":null},{"name":"Sancho","url":"http:\/\/twitter.com\/search?q=Sancho","promoted_content":null,"query":"Sancho","tweet_volume":null},{"name":"#HUBFORUM","url":"http:\/\/twitter.com\/search?q=%23HUBFORUM","promoted_content":null,"query":"%23HUBFORUM","tweet_volume":null},{"name":"Rekkles","url":"http:\/\/twitter.com\/search?q=Rekkles","promoted_content":null,"query":"Rekkles","tweet_volume":null},{"name":"Pierre Niney","url":"http:\/\/twitter.com\/search?q=%22Pierre+Niney%22","promoted_content":null,"query":"%22Pierre+Niney%22","tweet_volume":null},{"name":"Havertz","url":"http:\/\/twitter.com\/search?q=Havertz","promoted_content":null,"query":"Havertz","tweet_volume":null},{"name":"Jennifer Aniston","url":"http:\/\/twitter.com\/search?q=%22Jennifer+Aniston%22","promoted_content":null,"query":"%22Jennifer+Aniston%22","tweet_volume":18422},{"name":"Belles Filles","url":"http:\/\/twitter.com\/search?q=%22Belles+Filles%22","promoted_content":null,"query":"%22Belles+Filles%22","tweet_volume":null},{"name":"Le Tour","url":"http:\/\/twitter.com\/search?q=%22Le+Tour%22","promoted_content":null,"query":"%22Le+Tour%22","tweet_volume":null},{"name":"Planche","url":"http:\/\/twitter.com\/search?q=Planche","promoted_content":null,"query":"Planche","tweet_volume":null},{"name":"Nemesis","url":"http:\/\/twitter.com\/search?q=Nemesis","promoted_content":null,"query":"Nemesis","tweet_volume":null},{"name":"Christian Prudhomme","url":"http:\/\/twitter.com\/search?q=%22Christian+Prudhomme%22","promoted_content":null,"query":"%22Christian+Prudhomme%22","tweet_volume":null},{"name":"puy mary","url":"http:\/\/twitter.com\/search?q=%22puy+mary%22","promoted_content":null,"query":"%22puy+mary%22","tweet_volume":null},{"name":"Yves Thr\u00E9ard","url":"http:\/\/twitter.com\/search?q=%22Yves+Thr%C3%A9ard%22","promoted_content":null,"query":"%22Yves+Thr%C3%A9ard%22","tweet_volume":null},{"name":"bardet","url":"http:\/\/twitter.com\/search?q=bardet","promoted_content":null,"query":"bardet","tweet_volume":null},{"name":"Tour du Sud de la France","url":"http:\/\/twitter.com\/search?q=%22Tour+du+Sud+de+la+France%22","promoted_content":null,"query":"%22Tour+du+Sud+de+la+France%22","tweet_volume":null},{"name":"col de la loze","url":"http:\/\/twitter.com\/search?q=%22col+de+la+loze%22","promoted_content":null,"query":"%22col+de+la+loze%22","tweet_volume":null},{"name":"Firminy","url":"http:\/\/twitter.com\/search?q=Firminy","promoted_content":null,"query":"Firminy","tweet_volume":null},{"name":"Avril Lavigne","url":"http:\/\/twitter.com\/search?q=%22Avril+Lavigne%22","promoted_content":null,"query":"%22Avril+Lavigne%22","tweet_volume":null},{"name":"Crayon","url":"http:\/\/twitter.com\/search?q=Crayon","promoted_content":null,"query":"Crayon","tweet_volume":null},{"name":"#MaskSinger","url":"http:\/\/twitter.com\/search?q=%23MaskSinger","promoted_content":null,"query":"%23MaskSinger","tweet_volume":null},{"name":"#FreeBetSoFoot","url":"http:\/\/twitter.com\/search?q=%23FreeBetSoFoot","promoted_content":null,"query":"%23FreeBetSoFoot","tweet_volume":null},{"name":"#madebygoogle","url":"http:\/\/twitter.com\/search?q=%23madebygoogle","promoted_content":null,"query":"%23madebygoogle","tweet_volume":10619},{"name":"#MardiConseil","url":"http:\/\/twitter.com\/search?q=%23MardiConseil","promoted_content":null,"query":"%23MardiConseil","tweet_volume":null},{"name":"#ITAInnov","url":"http:\/\/twitter.com\/search?q=%23ITAInnov","promoted_content":null,"query":"%23ITAInnov","tweet_volume":null},{"name":"#FNCWIN","url":"http:\/\/twitter.com\/search?q=%23FNCWIN","promoted_content":null,"query":"%23FNCWIN","tweet_volume":null},{"name":"#AssisesAgriAgro2019","url":"http:\/\/twitter.com\/search?q=%23AssisesAgriAgro2019","promoted_content":null,"query":"%23AssisesAgriAgro2019","tweet_volume":null},{"name":"#IDFSmartServices","url":"http:\/\/twitter.com\/search?q=%23IDFSmartServices","promoted_content":null,"query":"%23IDFSmartServices","tweet_volume":null},{"name":"#ET15","url":"http:\/\/twitter.com\/search?q=%23ET15","promoted_content":null,"query":"%23ET15","tweet_volume":null},{"name":"#OSS117","url":"http:\/\/twitter.com\/search?q=%23OSS117","promoted_content":null,"query":"%23OSS117","tweet_volume":null},{"name":"#ArmeniaTakeOver","url":"http:\/\/twitter.com\/search?q=%23ArmeniaTakeOver","promoted_content":null,"query":"%23ArmeniaTakeOver","tweet_volume":null},{"name":"#Cergy","url":"http:\/\/twitter.com\/search?q=%23Cergy","promoted_content":null,"query":"%23Cergy","tweet_volume":null},{"name":"#TTFL","url":"http:\/\/twitter.com\/search?q=%23TTFL","promoted_content":null,"query":"%23TTFL","tweet_volume":null},{"name":"#PacteProductif","url":"http:\/\/twitter.com\/search?q=%23PacteProductif","promoted_content":null,"query":"%23PacteProductif","tweet_volume":null},{"name":"#mahoraistakeover","url":"http:\/\/twitter.com\/search?q=%23mahoraistakeover","promoted_content":null,"query":"%23mahoraistakeover","tweet_volume":null},{"name":"#bzbalsace","url":"http:\/\/twitter.com\/search?q=%23bzbalsace","promoted_content":null,"query":"%23bzbalsace","tweet_volume":null},{"name":"#PrayForLebanon","url":"http:\/\/twitter.com\/search?q=%23PrayForLebanon","promoted_content":null,"query":"%23PrayForLebanon","tweet_volume":23000},{"name":"#WFRE19","url":"http:\/\/twitter.com\/search?q=%23WFRE19","promoted_content":null,"query":"%23WFRE19","tweet_volume":null},{"name":"#sonicmovie","url":"http:\/\/twitter.com\/search?q=%23sonicmovie","promoted_content":null,"query":"%23sonicmovie","tweet_volume":null},{"name":"#PSGOM","url":"http:\/\/twitter.com\/search?q=%23PSGOM","promoted_content":null,"query":"%23PSGOM","tweet_volume":null},{"name":"#veauxlaitiers","url":"http:\/\/twitter.com\/search?q=%23veauxlaitiers","promoted_content":null,"query":"%23veauxlaitiers","tweet_volume":null},{"name":"#Arles","url":"http:\/\/twitter.com\/search?q=%23Arles","promoted_content":null,"query":"%23Arles","tweet_volume":null},{"name":"#redhatforumfr","url":"http:\/\/twitter.com\/search?q=%23redhatforumfr","promoted_content":null,"query":"%23redhatforumfr","tweet_volume":null},{"name":"#EntretiensCDV","url":"http:\/\/twitter.com\/search?q=%23EntretiensCDV","promoted_content":null,"query":"%23EntretiensCDV","tweet_volume":null},{"name":"#TDF2019","url":"http:\/\/twitter.com\/search?q=%23TDF2019","promoted_content":null,"query":"%23TDF2019","tweet_volume":null},{"name":"#LuigisMansion3","url":"http:\/\/twitter.com\/search?q=%23LuigisMansion3","promoted_content":null,"query":"%23LuigisMansion3","tweet_volume":null}],"as_of":"2019-10-15T14:34:44Z","created_at":"2019-10-15T14:29:19Z","locations":[{"name":"France","woeid":23424819}]}]