[{"trends":[{"name":"#\u0639\u0645\u0627\u0646_\u0642\u0637\u0631","url":"http:\/\/twitter.com\/search?q=%23%D8%B9%D9%85%D8%A7%D9%86_%D9%82%D8%B7%D8%B1","promoted_content":null,"query":"%23%D8%B9%D9%85%D8%A7%D9%86_%D9%82%D8%B7%D8%B1","tweet_volume":null},{"name":"#\u0644\u0628\u0646\u0627\u0646_\u064A\u062D\u062A\u0631\u0642","url":"http:\/\/twitter.com\/search?q=%23%D9%84%D8%A8%D9%86%D8%A7%D9%86_%D9%8A%D8%AD%D8%AA%D8%B1%D9%82","promoted_content":null,"query":"%23%D9%84%D8%A8%D9%86%D8%A7%D9%86_%D9%8A%D8%AD%D8%AA%D8%B1%D9%82","tweet_volume":164755},{"name":"#\u0645\u0631\u0627\u0633\u064A\u0645_\u0633\u0644\u0637\u0627\u0646\u064A\u0647","url":"http:\/\/twitter.com\/search?q=%23%D9%85%D8%B1%D8%A7%D8%B3%D9%8A%D9%85_%D8%B3%D9%84%D8%B7%D8%A7%D9%86%D9%8A%D9%87","promoted_content":null,"query":"%23%D9%85%D8%B1%D8%A7%D8%B3%D9%8A%D9%85_%D8%B3%D9%84%D8%B7%D8%A7%D9%86%D9%8A%D9%87","tweet_volume":null},{"name":"#\u0628\u0627\u062D\u062B\u0648\u0646_\u0639\u0646_\u0639\u0645\u0644_\u064A\u0633\u062A\u063A\u064A\u062B\u0648\u0646150","url":"http:\/\/twitter.com\/search?q=%23%D8%A8%D8%A7%D8%AD%D8%AB%D9%88%D9%86_%D8%B9%D9%86_%D8%B9%D9%85%D9%84_%D9%8A%D8%B3%D8%AA%D8%BA%D9%8A%D8%AB%D9%88%D9%86150","promoted_content":null,"query":"%23%D8%A8%D8%A7%D8%AD%D8%AB%D9%88%D9%86_%D8%B9%D9%86_%D8%B9%D9%85%D9%84_%D9%8A%D8%B3%D8%AA%D8%BA%D9%8A%D8%AB%D9%88%D9%86150","tweet_volume":null},{"name":"#\u0627\u0644\u0630\u0643\u0631\u064A_\u0627\u0644\u0639\u0645\u0627\u0646\u064A\u0647","url":"http:\/\/twitter.com\/search?q=%23%D8%A7%D9%84%D8%B0%D9%83%D8%B1%D9%8A_%D8%A7%D9%84%D8%B9%D9%85%D8%A7%D9%86%D9%8A%D9%87","promoted_content":null,"query":"%23%D8%A7%D9%84%D8%B0%D9%83%D8%B1%D9%8A_%D8%A7%D9%84%D8%B9%D9%85%D8%A7%D9%86%D9%8A%D9%87","tweet_volume":null},{"name":"\u062F\u064A\u0631\u0628\u064A \u0627\u0644\u063A\u0636\u0628","url":"http:\/\/twitter.com\/search?q=%22%D8%AF%D9%8A%D8%B1%D8%A8%D9%8A+%D8%A7%D9%84%D8%BA%D8%B6%D8%A8%22","promoted_content":null,"query":"%22%D8%AF%D9%8A%D8%B1%D8%A8%D9%8A+%D8%A7%D9%84%D8%BA%D8%B6%D8%A8%22","tweet_volume":null},{"name":"\u0627\u0644\u0645\u0631\u0627\u0647 \u0627\u0644\u0639\u0645\u0627\u0646\u064A\u0647","url":"http:\/\/twitter.com\/search?q=%22%D8%A7%D9%84%D9%85%D8%B1%D8%A7%D9%87+%D8%A7%D9%84%D8%B9%D9%85%D8%A7%D9%86%D9%8A%D9%87%22","promoted_content":null,"query":"%22%D8%A7%D9%84%D9%85%D8%B1%D8%A7%D9%87+%D8%A7%D9%84%D8%B9%D9%85%D8%A7%D9%86%D9%8A%D9%87%22","tweet_volume":null},{"name":"\u062C\u0647\u0627\u0632 \u0627\u0644\u0636\u0631\u0627\u064A\u0628","url":"http:\/\/twitter.com\/search?q=%22%D8%AC%D9%87%D8%A7%D8%B2+%D8%A7%D9%84%D8%B6%D8%B1%D8%A7%D9%8A%D8%A8%22","promoted_content":null,"query":"%22%D8%AC%D9%87%D8%A7%D8%B2+%D8%A7%D9%84%D8%B6%D8%B1%D8%A7%D9%8A%D8%A8%22","tweet_volume":null},{"name":"\u0627\u0628\u0648 \u0645\u0631\u064A\u0645","url":"http:\/\/twitter.com\/search?q=%22%D8%A7%D8%A8%D9%88+%D9%85%D8%B1%D9%8A%D9%85%22","promoted_content":null,"query":"%22%D8%A7%D8%A8%D9%88+%D9%85%D8%B1%D9%8A%D9%85%22","tweet_volume":null},{"name":"\u0642\u064A\u0633 \u0633\u0639\u064A\u062F","url":"http:\/\/twitter.com\/search?q=%22%D9%82%D9%8A%D8%B3+%D8%B3%D8%B9%D9%8A%D8%AF%22","promoted_content":null,"query":"%22%D9%82%D9%8A%D8%B3+%D8%B3%D8%B9%D9%8A%D8%AF%22","tweet_volume":40076},{"name":"Omani","url":"http:\/\/twitter.com\/search?q=Omani","promoted_content":null,"query":"Omani","tweet_volume":null},{"name":"\u0627\u0644\u0645\u0643\u0627\u0646 \u0627\u0644\u0645\u0646\u0627\u0633\u0628","url":"http:\/\/twitter.com\/search?q=%22%D8%A7%D9%84%D9%85%D9%83%D8%A7%D9%86+%D8%A7%D9%84%D9%85%D9%86%D8%A7%D8%B3%D8%A8%22","promoted_content":null,"query":"%22%D8%A7%D9%84%D9%85%D9%83%D8%A7%D9%86+%D8%A7%D9%84%D9%85%D9%86%D8%A7%D8%B3%D8%A8%22","tweet_volume":null},{"name":"\u0639\u0644\u064A \u0628\u0627\u0644\u064A","url":"http:\/\/twitter.com\/search?q=%22%D8%B9%D9%84%D9%8A+%D8%A8%D8%A7%D9%84%D9%8A%22","promoted_content":null,"query":"%22%D8%B9%D9%84%D9%8A+%D8%A8%D8%A7%D9%84%D9%8A%22","tweet_volume":null},{"name":"\u0628\u0646\u0643 \u0645\u0633\u0642\u0637","url":"http:\/\/twitter.com\/search?q=%22%D8%A8%D9%86%D9%83+%D9%85%D8%B3%D9%82%D8%B7%22","promoted_content":null,"query":"%22%D8%A8%D9%86%D9%83+%D9%85%D8%B3%D9%82%D8%B7%22","tweet_volume":null},{"name":"Muslim","url":"http:\/\/twitter.com\/search?q=Muslim","promoted_content":null,"query":"Muslim","tweet_volume":127880},{"name":"\u0639\u0644\u064A \u0627\u0644\u0628\u0627\u0644","url":"http:\/\/twitter.com\/search?q=%22%D8%B9%D9%84%D9%8A+%D8%A7%D9%84%D8%A8%D8%A7%D9%84%22","promoted_content":null,"query":"%22%D8%B9%D9%84%D9%8A+%D8%A7%D9%84%D8%A8%D8%A7%D9%84%22","tweet_volume":null},{"name":"\u0627\u0644\u0634\u0639\u0628 \u0627\u0644\u062A\u0648\u0646\u0633\u064A","url":"http:\/\/twitter.com\/search?q=%22%D8%A7%D9%84%D8%B4%D8%B9%D8%A8+%D8%A7%D9%84%D8%AA%D9%88%D9%86%D8%B3%D9%8A%22","promoted_content":null,"query":"%22%D8%A7%D9%84%D8%B4%D8%B9%D8%A8+%D8%A7%D9%84%D8%AA%D9%88%D9%86%D8%B3%D9%8A%22","tweet_volume":null},{"name":"\u0628\u0646\u062A \u0627\u0644\u062D\u0644\u0627\u0644","url":"http:\/\/twitter.com\/search?q=%22%D8%A8%D9%86%D8%AA+%D8%A7%D9%84%D8%AD%D9%84%D8%A7%D9%84%22","promoted_content":null,"query":"%22%D8%A8%D9%86%D8%AA+%D8%A7%D9%84%D8%AD%D9%84%D8%A7%D9%84%22","tweet_volume":null},{"name":"\u0627\u0644\u0644\u063A\u0647 \u0627\u0644\u0627\u0646\u062C\u0644\u064A\u0632\u064A\u0647","url":"http:\/\/twitter.com\/search?q=%22%D8%A7%D9%84%D9%84%D8%BA%D9%87+%D8%A7%D9%84%D8%A7%D9%86%D8%AC%D9%84%D9%8A%D8%B2%D9%8A%D9%87%22","promoted_content":null,"query":"%22%D8%A7%D9%84%D9%84%D8%BA%D9%87+%D8%A7%D9%84%D8%A7%D9%86%D8%AC%D9%84%D9%8A%D8%B2%D9%8A%D9%87%22","tweet_volume":null},{"name":"\u0627\u0628\u0648 \u0627\u062D\u0645\u062F","url":"http:\/\/twitter.com\/search?q=%22%D8%A7%D8%A8%D9%88+%D8%A7%D8%AD%D9%85%D8%AF%22","promoted_content":null,"query":"%22%D8%A7%D8%A8%D9%88+%D8%A7%D8%AD%D9%85%D8%AF%22","tweet_volume":null},{"name":"\u0645\u0648\u062A\u064A \u0627\u0644\u0645\u0633\u0644\u0645\u064A\u0646","url":"http:\/\/twitter.com\/search?q=%22%D9%85%D9%88%D8%AA%D9%8A+%D8%A7%D9%84%D9%85%D8%B3%D9%84%D9%85%D9%8A%D9%86%22","promoted_content":null,"query":"%22%D9%85%D9%88%D8%AA%D9%8A+%D8%A7%D9%84%D9%85%D8%B3%D9%84%D9%85%D9%8A%D9%86%22","tweet_volume":null},{"name":"absolutely","url":"http:\/\/twitter.com\/search?q=absolutely","promoted_content":null,"query":"absolutely","tweet_volume":350932},{"name":"#\u0646\u062F\u0627\u0621_\u0644\u0644\u0633\u0644\u0637\u0627\u0646_\u062A\u0631\u0642\u064A\u0627\u062A\u0646\u0627_\u0645\u0633\u062A\u062D\u0642\u064787","url":"http:\/\/twitter.com\/search?q=%23%D9%86%D8%AF%D8%A7%D8%A1_%D9%84%D9%84%D8%B3%D9%84%D8%B7%D8%A7%D9%86_%D8%AA%D8%B1%D9%82%D9%8A%D8%A7%D8%AA%D9%86%D8%A7_%D9%85%D8%B3%D8%AA%D8%AD%D9%82%D9%8787","promoted_content":null,"query":"%23%D9%86%D8%AF%D8%A7%D8%A1_%D9%84%D9%84%D8%B3%D9%84%D8%B7%D8%A7%D9%86_%D8%AA%D8%B1%D9%82%D9%8A%D8%A7%D8%AA%D9%86%D8%A7_%D9%85%D8%B3%D8%AA%D8%AD%D9%82%D9%8787","tweet_volume":null},{"name":"#Welcome_back_bedaya","url":"http:\/\/twitter.com\/search?q=%23Welcome_back_bedaya","promoted_content":null,"query":"%23Welcome_back_bedaya","tweet_volume":null},{"name":"#\u064A\u0648\u0645_\u0627\u0644\u0645\u0631\u0627\u0647_\u0627\u0644\u0639\u0645\u0627\u0646\u064A\u0647","url":"http:\/\/twitter.com\/search?q=%23%D9%8A%D9%88%D9%85_%D8%A7%D9%84%D9%85%D8%B1%D8%A7%D9%87_%D8%A7%D9%84%D8%B9%D9%85%D8%A7%D9%86%D9%8A%D9%87","promoted_content":null,"query":"%23%D9%8A%D9%88%D9%85_%D8%A7%D9%84%D9%85%D8%B1%D8%A7%D9%87_%D8%A7%D9%84%D8%B9%D9%85%D8%A7%D9%86%D9%8A%D9%87","tweet_volume":null},{"name":"#\u0642\u064A\u0633_\u0633\u0639\u064A\u062F","url":"http:\/\/twitter.com\/search?q=%23%D9%82%D9%8A%D8%B3_%D8%B3%D8%B9%D9%8A%D8%AF","promoted_content":null,"query":"%23%D9%82%D9%8A%D8%B3_%D8%B3%D8%B9%D9%8A%D8%AF","tweet_volume":15497},{"name":"#\u0634\u0643\u0631\u0627_\u0633\u0627\u0644\u0645_\u0639\u0648\u0641\u064A\u062A","url":"http:\/\/twitter.com\/search?q=%23%D8%B4%D9%83%D8%B1%D8%A7_%D8%B3%D8%A7%D9%84%D9%85_%D8%B9%D9%88%D9%81%D9%8A%D8%AA","promoted_content":null,"query":"%23%D8%B4%D9%83%D8%B1%D8%A7_%D8%B3%D8%A7%D9%84%D9%85_%D8%B9%D9%88%D9%81%D9%8A%D8%AA","tweet_volume":null},{"name":"#\u0645\u0631\u0643\u0632_\u0633\u0644\u0627\u0645\u0647_\u0648\u062C\u0648\u062F\u0647_\u0627\u0644\u063A\u0630\u0627\u0621","url":"http:\/\/twitter.com\/search?q=%23%D9%85%D8%B1%D9%83%D8%B2_%D8%B3%D9%84%D8%A7%D9%85%D9%87_%D9%88%D8%AC%D9%88%D8%AF%D9%87_%D8%A7%D9%84%D8%BA%D8%B0%D8%A7%D8%A1","promoted_content":null,"query":"%23%D9%85%D8%B1%D9%83%D8%B2_%D8%B3%D9%84%D8%A7%D9%85%D9%87_%D9%88%D8%AC%D9%88%D8%AF%D9%87_%D8%A7%D9%84%D8%BA%D8%B0%D8%A7%D8%A1","tweet_volume":null},{"name":"#\u062A\u0648\u0646\u0633","url":"http:\/\/twitter.com\/search?q=%23%D8%AA%D9%88%D9%86%D8%B3","promoted_content":null,"query":"%23%D8%AA%D9%88%D9%86%D8%B3","tweet_volume":19695},{"name":"#\u0635\u0628\u0627\u062D_\u0627\u0644\u062E\u064A\u0631","url":"http:\/\/twitter.com\/search?q=%23%D8%B5%D8%A8%D8%A7%D8%AD_%D8%A7%D9%84%D8%AE%D9%8A%D8%B1","promoted_content":null,"query":"%23%D8%B5%D8%A8%D8%A7%D8%AD_%D8%A7%D9%84%D8%AE%D9%8A%D8%B1","tweet_volume":74619},{"name":"#\u0648\u0632\u0627\u0631\u0647_\u0634\u0648\u0648\u0646_\u0627\u0644\u0641\u0646\u0648\u0646","url":"http:\/\/twitter.com\/search?q=%23%D9%88%D8%B2%D8%A7%D8%B1%D9%87_%D8%B4%D9%88%D9%88%D9%86_%D8%A7%D9%84%D9%81%D9%86%D9%88%D9%86","promoted_content":null,"query":"%23%D9%88%D8%B2%D8%A7%D8%B1%D9%87_%D8%B4%D9%88%D9%88%D9%86_%D8%A7%D9%84%D9%81%D9%86%D9%88%D9%86","tweet_volume":null},{"name":"#\u062C\u0631\u064A\u062F\u0647_\u0639\u0645\u0627\u0646","url":"http:\/\/twitter.com\/search?q=%23%D8%AC%D8%B1%D9%8A%D8%AF%D9%87_%D8%B9%D9%85%D8%A7%D9%86","promoted_content":null,"query":"%23%D8%AC%D8%B1%D9%8A%D8%AF%D9%87_%D8%B9%D9%85%D8%A7%D9%86","tweet_volume":null},{"name":"#OmanObserver","url":"http:\/\/twitter.com\/search?q=%23OmanObserver","promoted_content":null,"query":"%23OmanObserver","tweet_volume":null},{"name":"#\u0641\u0648\u0631\u062A\u0646\u0627\u064A\u062A","url":"http:\/\/twitter.com\/search?q=%23%D9%81%D9%88%D8%B1%D8%AA%D9%86%D8%A7%D9%8A%D8%AA","promoted_content":null,"query":"%23%D9%81%D9%88%D8%B1%D8%AA%D9%86%D8%A7%D9%8A%D8%AA","tweet_volume":null},{"name":"#Fortnite","url":"http:\/\/twitter.com\/search?q=%23Fortnite","promoted_content":null,"query":"%23Fortnite","tweet_volume":233518},{"name":"#\u064A\u062D\u062F\u062B_\u0627\u0644\u0627\u0646","url":"http:\/\/twitter.com\/search?q=%23%D9%8A%D8%AD%D8%AF%D8%AB_%D8%A7%D9%84%D8%A7%D9%86","promoted_content":null,"query":"%23%D9%8A%D8%AD%D8%AF%D8%AB_%D8%A7%D9%84%D8%A7%D9%86","tweet_volume":null},{"name":"#\u062C\u0631\u064A\u062F\u0647_\u0627\u0644\u0631\u0648\u064A\u0647","url":"http:\/\/twitter.com\/search?q=%23%D8%AC%D8%B1%D9%8A%D8%AF%D9%87_%D8%A7%D9%84%D8%B1%D9%88%D9%8A%D9%87","promoted_content":null,"query":"%23%D8%AC%D8%B1%D9%8A%D8%AF%D9%87_%D8%A7%D9%84%D8%B1%D9%88%D9%8A%D9%87","tweet_volume":null},{"name":"#ocpc2019","url":"http:\/\/twitter.com\/search?q=%23ocpc2019","promoted_content":null,"query":"%23ocpc2019","tweet_volume":null},{"name":"#\u0645\u0633\u0631\u062D\u064A\u0647_\u0648\u0644\u062F_\u0627\u0644\u0628\u0644\u062F","url":"http:\/\/twitter.com\/search?q=%23%D9%85%D8%B3%D8%B1%D8%AD%D9%8A%D9%87_%D9%88%D9%84%D8%AF_%D8%A7%D9%84%D8%A8%D9%84%D8%AF","promoted_content":null,"query":"%23%D9%85%D8%B3%D8%B1%D8%AD%D9%8A%D9%87_%D9%88%D9%84%D8%AF_%D8%A7%D9%84%D8%A8%D9%84%D8%AF","tweet_volume":null},{"name":"#\u0627\u0644\u0634\u0628\u064A\u0628\u0647","url":"http:\/\/twitter.com\/search?q=%23%D8%A7%D9%84%D8%B4%D8%A8%D9%8A%D8%A8%D9%87","promoted_content":null,"query":"%23%D8%A7%D9%84%D8%B4%D8%A8%D9%8A%D8%A8%D9%87","tweet_volume":null},{"name":"#\u0627\u0644\u0648\u0639\u062F_\u0627\u0633\u062A\u0627\u062F_\u0627\u0644\u062C\u0646\u0648\u0628","url":"http:\/\/twitter.com\/search?q=%23%D8%A7%D9%84%D9%88%D8%B9%D8%AF_%D8%A7%D8%B3%D8%AA%D8%A7%D8%AF_%D8%A7%D9%84%D8%AC%D9%86%D9%88%D8%A8","promoted_content":null,"query":"%23%D8%A7%D9%84%D9%88%D8%B9%D8%AF_%D8%A7%D8%B3%D8%AA%D8%A7%D8%AF_%D8%A7%D9%84%D8%AC%D9%86%D9%88%D8%A8","tweet_volume":null},{"name":"#\u0641\u0639\u0627\u0644\u064A\u0627\u062A_\u062A\u0639\u0644\u064A\u0645\u064A\u0647_\u0634\u0645\u0627\u0644_\u0627\u0644\u0628\u0627\u0637\u0646\u0647","url":"http:\/\/twitter.com\/search?q=%23%D9%81%D8%B9%D8%A7%D9%84%D9%8A%D8%A7%D8%AA_%D8%AA%D8%B9%D9%84%D9%8A%D9%85%D9%8A%D9%87_%D8%B4%D9%85%D8%A7%D9%84_%D8%A7%D9%84%D8%A8%D8%A7%D8%B7%D9%86%D9%87","promoted_content":null,"query":"%23%D9%81%D8%B9%D8%A7%D9%84%D9%8A%D8%A7%D8%AA_%D8%AA%D8%B9%D9%84%D9%8A%D9%85%D9%8A%D9%87_%D8%B4%D9%85%D8%A7%D9%84_%D8%A7%D9%84%D8%A8%D8%A7%D8%B7%D9%86%D9%87","tweet_volume":null},{"name":"#\u0628\u0646\u0643_\u0645\u0633\u0642\u0637","url":"http:\/\/twitter.com\/search?q=%23%D8%A8%D9%86%D9%83_%D9%85%D8%B3%D9%82%D8%B7","promoted_content":null,"query":"%23%D8%A8%D9%86%D9%83_%D9%85%D8%B3%D9%82%D8%B7","tweet_volume":null},{"name":"#\u0627\u062B\u064A\u0631","url":"http:\/\/twitter.com\/search?q=%23%D8%A7%D8%AB%D9%8A%D8%B1","promoted_content":null,"query":"%23%D8%A7%D8%AB%D9%8A%D8%B1","tweet_volume":null},{"name":"#\u0634\u0628\u0643\u0647_\u0627\u0644\u0631\u064A\u062D_\u0644\u0644\u0637\u0642\u0633","url":"http:\/\/twitter.com\/search?q=%23%D8%B4%D8%A8%D9%83%D9%87_%D8%A7%D9%84%D8%B1%D9%8A%D8%AD_%D9%84%D9%84%D8%B7%D9%82%D8%B3","promoted_content":null,"query":"%23%D8%B4%D8%A8%D9%83%D9%87_%D8%A7%D9%84%D8%B1%D9%8A%D8%AD_%D9%84%D9%84%D8%B7%D9%82%D8%B3","tweet_volume":null},{"name":"#smart_x","url":"http:\/\/twitter.com\/search?q=%23smart_x","promoted_content":null,"query":"%23smart_x","tweet_volume":null},{"name":"#\u0645\u0631\u0643\u0632_\u0627\u0644\u0627\u062E\u0628\u0627\u0631","url":"http:\/\/twitter.com\/search?q=%23%D9%85%D8%B1%D9%83%D8%B2_%D8%A7%D9%84%D8%A7%D8%AE%D8%A8%D8%A7%D8%B1","promoted_content":null,"query":"%23%D9%85%D8%B1%D9%83%D8%B2_%D8%A7%D9%84%D8%A7%D8%AE%D8%A8%D8%A7%D8%B1","tweet_volume":null},{"name":"#Bigil","url":"http:\/\/twitter.com\/search?q=%23Bigil","promoted_content":null,"query":"%23Bigil","tweet_volume":211923},{"name":"#bb13","url":"http:\/\/twitter.com\/search?q=%23bb13","promoted_content":null,"query":"%23bb13","tweet_volume":24382}],"as_of":"2019-10-15T14:36:12Z","created_at":"2019-10-15T14:33:33Z","locations":[{"name":"Oman","woeid":23424898}]}]